vivarium/core/__init__.py
vivarium/core/composition.py
vivarium/core/emitter.py
vivarium/core/experiment.py
vivarium/core/process.py
vivarium/core/registry.py
vivarium/library/__init__.py
vivarium/library/datum.py
vivarium/library/dict_utils.py
vivarium/library/fasta.py
vivarium/library/filepath.py
vivarium/library/make_network.py
vivarium/library/path.py
vivarium/library/pretty.py
vivarium/library/timeseries.py
vivarium/library/units.py
vivarium/processes/__init__.py
vivarium/processes/meta_division.py
vivarium/processes/nonspatial_environment.py
vivarium/processes/template_process.py
vivarium/processes/timeline.py
vivarium/processes/tree_mass.py
vivarium_core-0.0.8.dist-info/METADATA
vivarium_core-0.0.8.dist-info/WHEEL
vivarium_core-0.0.8.dist-info/entry_points.txt
vivarium_core-0.0.8.dist-info/top_level.txt
vivarium_core-0.0.8.dist-info/RECORD
