Metadata-Version: 2.1
Name: vivarium-core
Version: 0.0.8
Summary: UNKNOWN
Home-page: https://github.com/vivarium-collective/vivarium-core
Author: Eran Agmon, Ryan Spangler
Author-email: eagmon@stanford.edu, ryan.spangler@gmail.com
License: MIT
Platform: UNKNOWN
Requires-Dist: confluent-kafka
Requires-Dist: matplotlib
Requires-Dist: networkx
Requires-Dist: numpy
Requires-Dist: Pint
Requires-Dist: pymongo
Requires-Dist: pytest
Requires-Dist: scipy
